robosoc2dplot/__init__.py
robosoc2dplot/plot.py
robosoc2dplot-1.0.0.dist-info/LICENSE
robosoc2dplot-1.0.0.dist-info/METADATA
robosoc2dplot-1.0.0.dist-info/WHEEL
robosoc2dplot-1.0.0.dist-info/top_level.txt
robosoc2dplot-1.0.0.dist-info/RECORD
